cmd_client/__init__.py
cmd_client/console.py
cmd_client/errors.py
cmd_client/parser.py
cmd_client/test.py
cmd_client/version.py
cmd_client/commands/__init__.py
cmd_client/commands/active_simulations.py
cmd_client/commands/run_scenario.py
cmd_client/commands/run_suite.py
cmd_client/commands/settings.py
cmd_client/commands/slack_notify.py
cmd_client/commands/utils.py
cmd_client/models/__init__.py
cmd_client/models/actions.py
cmd_client/models/base.py
cmd_client/models/boundary_conditions.py
cmd_client/models/breach.py
cmd_client/models/errors.py
cmd_client/models/initial_waterlevels.py
cmd_client/models/lateral.py
cmd_client/models/monitor.py
cmd_client/models/rain.py
cmd_client/models/rasteredit.py
cmd_client/models/savedstate.py
cmd_client/models/scenario.py
cmd_client/models/simulation.py
cmd_client/models/sources_sinks.py
cmd_client/models/structure_control.py
cmd_client/models/waitfor.py
cmd_client/models/wind.py
cmd_client/websockets/__init__.py
cmd_client/websockets/clients.py
3Di_cmd_client-0.0.3.dist-info/AUTHORS.rst
3Di_cmd_client-0.0.3.dist-info/LICENSE
3Di_cmd_client-0.0.3.dist-info/METADATA
3Di_cmd_client-0.0.3.dist-info/WHEEL
3Di_cmd_client-0.0.3.dist-info/entry_points.txt
3Di_cmd_client-0.0.3.dist-info/top_level.txt
3Di_cmd_client-0.0.3.dist-info/RECORD
