Metadata-Version: 2.1
Name: 3Di-cmd-client
Version: 0.0.3
Summary: Python 3Di command line client
Home-page: https://github.com/nens/3Di-cmd
Author: Jelle Prins
Author-email: info@nelen-schuurmans.nl
License: MIT license
Keywords: 3Di,client,command line,scenario
Platform: UNKNOWN
Classifier: Development Status :: 4 - Beta
Classifier: Intended Audience :: Developers
Classifier: License :: OSI Approved :: BSD License
Classifier: Natural Language :: English
Classifier: Programming Language :: Python :: 3
Classifier: Topic :: Scientific/Engineering
Requires-Python: >=3.8
Requires-Dist: threedi-api-client (==3.0.17)
Requires-Dist: PyYAML (==5.1)
Requires-Dist: websockets (==8.1)
Requires-Dist: arrow (==0.14.4)
Requires-Dist: Jinja2 (==2.10.1)
Requires-Dist: jinja2-time (==0.2.0)
Requires-Dist: slackclient (==2.8.2)
Requires-Dist: click (==7.1.2)
Requires-Dist: requests (==2.25.0)
Requires-Dist: rich (==9.4.0)
